scircm/__init__.py
scircm/__main__.py
scircm/base.py
scircm/dna_rna.py
scircm/old_vis.py
scircm/randm.py
scircm/rcm_noprot.py
scircm/rna_protein.py
scircm/stats.py
scircm/vae.py
scircm/vis.py
scircm-1.1.5.data/data/LICENSE
scircm-1.1.5.dist-info/LICENSE
scircm-1.1.5.dist-info/METADATA
scircm-1.1.5.dist-info/WHEEL
scircm-1.1.5.dist-info/entry_points.txt
scircm-1.1.5.dist-info/top_level.txt
scircm-1.1.5.dist-info/RECORD
