Metadata-Version: 2.1
Name: scircm
Version: 1.1.5
Home-page: https://github.com/ArianeMora/scircm
Author: Ariane Mora
Author-email: ariane.n.mora@gmail.com
License: GPL3
Project-URL: Bug Tracker, https://github.com/ArianeMora/scircm/issues
Project-URL: Documentation, https://github.com/ArianeMora/scircm
Project-URL: Source Code, https://github.com/ArianeMora/scircm
Keywords: epigenetics,bioinformatics
Classifier: Intended Audience :: Science/Research
Classifier: License :: OSI Approved :: GNU General Public License v3 (GPLv3)
Classifier: Natural Language :: English
Classifier: Operating System :: OS Independent
Classifier: Programming Language :: Python :: 3.6
Classifier: Programming Language :: Python :: 3.7
Classifier: Programming Language :: Python :: 3.8
Classifier: Topic :: Scientific/Engineering :: Bio-Informatics
Requires-Python: >=3.6
License-File: LICENSE
Requires-Dist: pandas
Requires-Dist: numpy
Requires-Dist: scibiomart
Requires-Dist: sciutil>=1.0.3
Requires-Dist: scivae
Requires-Dist: scikit-learn
Requires-Dist: sciviso
Requires-Dist: seaborn
Requires-Dist: stats
Requires-Dist: matplotlib-venn
Requires-Dist: scimotf
Requires-Dist: scie2g
